{
    "ovrLvbNm": "남방방게",
    "ovrLvbEngNm": "Pseudohelice subquadrata",
    "ovrLvbCd": "subquadrata",
    "ovrFileNm": "05.png",
    "frstRegDtlDt": "2019-01-22 11:09:00.0",
    "ovrDelYn": "N",
    "ovrSortSeq1": "6",
    "ovrSortSeq2": "5",
    "ovrGlbFileNm": "201805.glb",
    "ovrHbttNm": "갯벌",
    "ovrClassNm": "무척추동물",
    "ovrMrpoKnd": "해양보호생물",
    "ovrStleDstcftCn": "등껍질은 사각형이며, 가로 길이가 세로 길이보다 넓습니다. 눈구멍 뒤에 4개의 이빨 모양의 돌기가 있습니다. 등껍질에는 작은 과립들과 짧은 털이 촘촘하게 나있습니다. 손바닥의 양면이 볼록하고, 눈 아래 두둑 위에는 작은 과립이 16~17개 촘촘히 배열되어 있습니다.",
    "ovrEcgyDstcftCn": "암석이 많은 모래펄 지역에 구멍을 파고 살고 있습니다.",
    "ovrDsrbCn": "일본, 타이완, 사이판 등에 분포하는 남방형으로 우리나라에서는 거문도, 부산, 제주도 등지에서 발견되었습니다.",
    "ovrSn": "40"
}