{
    "ovrLvbNm": "망상맵시산호",
    "ovrLvbEngNm": "Echinogorgia reticulata (Esper, 1791)",
    "ovrLvbCd": "echinogorgia",
    "ovrFileNm": "10.png",
    "frstRegDtlDt": "2019-01-22 11:09:00.0",
    "ovrDelYn": "N",
    "ovrSortSeq1": "6",
    "ovrSortSeq2": "10",
    "ovrGlbFileNm": "201810.glb",
    "ovrHbttNm": "바닷속암반",
    "ovrClassNm": "무척추동물",
    "ovrMrpoKnd": "해양보호생물",
    "ovrStleDstcftCn": "몸통은 부채모양이며 선명한 붉은색을 띱니다. 몸통의 높이는 약 20cm정도이고, 폭은 이보다 조금 더 넓습니다.",
    "ovrEcgyDstcftCn": "제주도 서귀포 문섬, 범섬에 서식합니다.",
    "ovrDsrbCn": "제주도 서귀포 및 남제주군 남원읍 해역에서 발견된 기록이 있지만, 최근에는 발견되지 않고 있습니다.",
    "ovrSn": "45"
}