{
    "ovrLvbNm": "흑범고래",
    "ovrLvbEngNm": "Pseudorca crassidens",
    "ovrLvbCd": "",
    "ovrFileNm": "",
    "frstRegDtlDt": "2023-01-06 10:33:00.643734",
    "ovrDelYn": "N",
    "ovrSortSeq1": "",
    "ovrSortSeq2": "",
    "ovrGlbFileNm": "202203.glb",
    "ovrHbttNm": "바다",
    "ovrClassNm": "포유류",
    "ovrMrpoKnd": "해양보호생물",
    "ovrStleDstcftCn": "범고래와 비슷하나 전신이 흑색이며 몸체는 가늘고 깁니다. 가슴지느러미 사이의 복부는 약간 밝은 흑색이고, 머리는 작고 이마가 둥글며 뾰족합니다. 부리는 완전히 없고 입은 후방으로 치켜 올라가 있으며, 위턱이 아래턱보다 깁니다. 좌우 측에 흑색 반점이 있는 개체들이 있으며 아래위턱 좌우에 각각 8～11개의 날카로운 이빨을 가지고 있습니다. 등지느러미는 넓은 낫 모양으로 끝부분은 가늘고 약간 아래로 쳐져 있는 것이 특징이며, 몸길이는 약 3.9～6.0m, 무게는 약 2톤가량으로 수컷이 암컷보다 다소 큽니다.",
    "ovrEcgyDstcftCn": "7년에 1회 계절에 관계없이 출산하며 수명은 수컷은 최대 56년, 암컷은 62년 정도로 알려져 있습니다. 어류와 오징어를 주 먹이로 하며 소형 고래류와 대형 고래류를 공격하기도 합니다.",
    "ovrDsrbCn": "북위 50도와 남위 50도 사이의 열대와 온대의 외양에 분포하며 우리나라에는 수온이 17도 이상이 되는 5～7월에 출현합니다.",
    "ovrSn": "89"
}